<?xml version="1.0" encoding="UTF-8"?>
<QCARConfig xmlns:xsi="http://www.w3.org/2001/XMLSchema-instance" xsi:noNamespaceSchemaLocation="qcar_config.xsd">
  <Tracking>
    <ImageTarget name="target_zemaitkiemis" size="2.000000 1.433790" />
    <ImageTarget name="target_vu_observ_kiemas" size="20.000000 33.176334" />
    <ImageTarget name="target_vepriai" size="1.000000 1.184801" />
    <ImageTarget name="target_Valiulio_akmuo" size="3.000000 2.126033" />
    <ImageTarget name="target_institutas_gostauto" size="1.000000 0.750000" />
    <ImageTarget name="Target_institutas" size="20.000000 15.000000" />
    <ImageTarget name="targetas_struve" size="2.000000 1.823183" />
    <ImageTarget name="laikrodis_1" size="20.000000 15.000000" />
    <ImageTarget name="Target_Kauno_fortas" size="2.000000 2.965221" />
    <ImageTarget name="nano_avionics" size="50.000000 66.666664" />
    <ImageTarget name="venera" size="0.200000 0.205969" />
    <ImageTarget name="saturnas" size="0.200000 0.199457" />
    <ImageTarget name="neptunas" size="0.200000 0.196170" />
    <ImageTarget name="marsas" size="0.200000 0.198527" />
    <ImageTarget name="jupiteris" size="0.200000 0.209690" />
    <ImageTarget name="Target_ciurlionis" size="10.000000 7.500000" />
    <ImageTarget name="Target_Andrioniskis" size="2.000000 2.666667" />
    <ImageTarget name="Target_birutes" size="3000.000000 2978.000000" />
  </Tracking>
</QCARConfig>
